{"nodes": [{"id": "readme_al_shabab", "label": "al Shabab (modpack)", "file_type": "concept", "source_file": "README.md", "source_location": null, "source_url": null, "captured_at": null, "author": null, "contributor": null, "rationale": "RPG sandbox pack on three pillars: RLCraft's systems without its frustration, Better MC's world, and a Create + physics-vehicles tech stack."}, {"id": "readme_minecraft", "label": "Minecraft 1.20.1", "file_type": "concept", "source_file": "README.md", "source_location": null, "source_url": null, "captured_at": null, "author": null, "contributor": null}, {"id": "readme_forge", "label": "Forge 47.4.x", "file_type": "concept", "source_file": "README.md", "source_location": null, "source_url": null, "captured_at": null, "author": null, "contributor": null}, {"id": "readme_rlcraft", "label": "RLCraft", "file_type": "concept", "source_file": "README.md", "source_location": null, "source_url": null, "captured_at": null, "author": null, "contributor": null}, {"id": "readme_better_mc", "label": "Better MC", "file_type": "concept", "source_file": "README.md", "source_location": null, "source_url": null, "captured_at": null, "author": null, "contributor": null}, {"id": "readme_create", "label": "Create", "file_type": "concept", "source_file": "README.md", "source_location": null, "source_url": null, "captured_at": null, "author": null, "contributor": null}, {"id": "readme_packwiz", "label": "packwiz", "file_type": "concept", "source_file": "README.md", "source_location": null, "source_url": null, "captured_at": null, "author": null, "contributor": null, "rationale": "pack/ is the single source of truth; every mod is a pinned .pw.toml. Preferred add order: Modrinth then CurseForge."}, {"id": "readme_packwiz_installer", "label": "packwiz-installer-bootstrap", "file_type": "concept", "source_file": "README.md", "source_location": null, "source_url": null, "captured_at": null, "author": null, "contributor": null}, {"id": "readme_github_pages", "label": "GitHub Pages", "file_type": "concept", "source_file": "README.md", "source_location": null, "source_url": null, "captured_at": null, "author": null, "contributor": null, "rationale": "pack/ is published to Pages; that one URL feeds server self-updates, client updaters, and tagged releases."}, {"id": "readme_pack_dir", "label": "pack/ (packwiz root)", "file_type": "concept", "source_file": "README.md", "source_location": null, "source_url": null, "captured_at": null, "author": null, "contributor": null}, {"id": "readme_server_dir", "label": "server/ self-bootstrapping scripts", "file_type": "concept", "source_file": "README.md", "source_location": null, "source_url": null, "captured_at": null, "author": null, "contributor": null}, {"id": "readme_client_dir", "label": "client/ installers", "file_type": "concept", "source_file": "README.md", "source_location": null, "source_url": null, "captured_at": null, "author": null, "contributor": null}], "edges": [{"source": "readme_al_shabab", "target": "readme_minecraft", "relation": "references", "confidence": "EXTRACTED", "confidence_score": 1.0, "source_file": "README.md", "source_location": null, "weight": 1.0}, {"source": "readme_al_shabab", "target": "readme_forge", "relation": "references", "confidence": "EXTRACTED", "confidence_score": 1.0, "source_file": "README.md", "source_location": null, "weight": 1.0}, {"source": "readme_al_shabab", "target": "readme_rlcraft", "relation": "conceptually_related_to", "confidence": "EXTRACTED", "confidence_score": 1.0, "source_file": "README.md", "source_location": null, "weight": 1.0}, {"source": "readme_al_shabab", "target": "readme_better_mc", "relation": "conceptually_related_to", "confidence": "EXTRACTED", "confidence_score": 1.0, "source_file": "README.md", "source_location": null, "weight": 1.0}, {"source": "readme_al_shabab", "target": "readme_create", "relation": "conceptually_related_to", "confidence": "EXTRACTED", "confidence_score": 1.0, "source_file": "README.md", "source_location": null, "weight": 1.0}, {"source": "readme_al_shabab", "target": "readme_pack_dir", "relation": "references", "confidence": "EXTRACTED", "confidence_score": 1.0, "source_file": "README.md", "source_location": null, "weight": 1.0}, {"source": "readme_al_shabab", "target": "readme_server_dir", "relation": "references", "confidence": "EXTRACTED", "confidence_score": 1.0, "source_file": "README.md", "source_location": null, "weight": 1.0}, {"source": "readme_al_shabab", "target": "readme_client_dir", "relation": "references", "confidence": "EXTRACTED", "confidence_score": 1.0, "source_file": "README.md", "source_location": null, "weight": 1.0}, {"source": "readme_pack_dir", "target": "readme_packwiz", "relation": "references", "confidence": "EXTRACTED", "confidence_score": 1.0, "source_file": "README.md", "source_location": null, "weight": 1.0}, {"source": "readme_pack_dir", "target": "readme_github_pages", "relation": "references", "confidence": "EXTRACTED", "confidence_score": 1.0, "source_file": "README.md", "source_location": null, "weight": 1.0}, {"source": "readme_server_dir", "target": "readme_packwiz_installer", "relation": "references", "confidence": "EXTRACTED", "confidence_score": 1.0, "source_file": "README.md", "source_location": null, "weight": 1.0}, {"source": "readme_client_dir", "target": "client_readme_update_bat", "relation": "references", "confidence": "EXTRACTED", "confidence_score": 1.0, "source_file": "README.md", "source_location": null, "weight": 1.0}, {"source": "readme_packwiz_installer", "target": "readme_packwiz", "relation": "conceptually_related_to", "confidence": "INFERRED", "confidence_score": 0.95, "source_file": "README.md", "source_location": null, "weight": 1.0}], "hyperedges": [{"id": "distribution_pipeline", "label": "Single-URL distribution pipeline", "nodes": ["readme_pack_dir", "readme_github_pages", "setup_pack_url", "readme_packwiz_installer", "release_release"], "relation": "participate_in", "confidence": "INFERRED", "confidence_score": 0.85, "source_file": "README.md"}]}